odoo/addons/delivery_roulier_chronopost_fr/README.rst
odoo/addons/delivery_roulier_chronopost_fr/__init__.py
odoo/addons/delivery_roulier_chronopost_fr/__manifest__.py
odoo/addons/delivery_roulier_chronopost_fr/data/delivery.xml
odoo/addons/delivery_roulier_chronopost_fr/data/product.xml
odoo/addons/delivery_roulier_chronopost_fr/i18n/delivery_roulier_chronopost_fr.pot
odoo/addons/delivery_roulier_chronopost_fr/models/__init__.py
odoo/addons/delivery_roulier_chronopost_fr/models/carrier_account.py
odoo/addons/delivery_roulier_chronopost_fr/models/delivery_carrier.py
odoo/addons/delivery_roulier_chronopost_fr/models/stock_picking.py
odoo/addons/delivery_roulier_chronopost_fr/models/stock_quant_package.py
odoo/addons/delivery_roulier_chronopost_fr/readme/CONTRIBUTORS.rst
odoo/addons/delivery_roulier_chronopost_fr/readme/DESCRIPTION.rst
odoo/addons/delivery_roulier_chronopost_fr/readme/ROADMAP.rst
odoo/addons/delivery_roulier_chronopost_fr/static/description/icon.png
odoo/addons/delivery_roulier_chronopost_fr/static/description/index.html
odoo/addons/delivery_roulier_chronopost_fr/tests/__init__.py
odoo/addons/delivery_roulier_chronopost_fr/tests/test_label_chronopost.py
odoo/addons/delivery_roulier_chronopost_fr/tests/cassettes/ChronopostLabelCase.test_labels.yaml
odoo/addons/delivery_roulier_chronopost_fr/views/carrier_account.xml
odoo14_addon_delivery_roulier_chronopost_fr-14.0.1.0.1.dist-info/METADATA
odoo14_addon_delivery_roulier_chronopost_fr-14.0.1.0.1.dist-info/WHEEL
odoo14_addon_delivery_roulier_chronopost_fr-14.0.1.0.1.dist-info/top_level.txt
odoo14_addon_delivery_roulier_chronopost_fr-14.0.1.0.1.dist-info/RECORD
